londonaicentre_oncollama_assets-1.0.5.dist-info/licenses/LICENSE.md
oncollama_assets/__init__.py
oncollama_assets/py.typed
oncollama_assets/schema.py
oncollama_assets/wrapper.py
oncollama_assets/prompts/systemprompt_datagen.md
oncollama_assets/prompts/systemprompt_finetune.md
oncollama_assets/prompts/systemprompt_infer.md
londonaicentre_oncollama_assets-1.0.5.dist-info/METADATA
londonaicentre_oncollama_assets-1.0.5.dist-info/WHEEL
londonaicentre_oncollama_assets-1.0.5.dist-info/top_level.txt
londonaicentre_oncollama_assets-1.0.5.dist-info/RECORD
