Metadata-Version: 2.4
Name: londonaicentre-oncollama-assets
Version: 1.0.5
Summary: OncoLlama assets
Author-email: "Dr. Joe Zhang" <jzhang@nhs.net>, "Dr. Martin Chapman" <martin.chapman@nhs.net>, "Dr. Lawrence Adams" <lawrence.adams2@nhs.net>
License-Expression: LicenseRef-Proprietary
Requires-Python: >=3.12
License-File: LICENSE.md
Requires-Dist: londonaicentre-schemallama-types
Requires-Dist: pydantic>=2.12.5
Dynamic: license-file
